str2float/__init__.py
str2float-0.0.9.dist-info/LICENSE
str2float-0.0.9.dist-info/METADATA
str2float-0.0.9.dist-info/WHEEL
str2float-0.0.9.dist-info/top_level.txt
str2float-0.0.9.dist-info/RECORD
