Metadata-Version: 2.1
Name: str2float
Version: 0.0.9
Summary: Convert float string (decimal point or decimal comma) to float
Home-page: https://github.com/Yellorn/str2float
Author: Hoang Yell
Author-email: hoangyell@yellorn.com
Classifier: Programming Language :: Python :: 3
Classifier: License :: OSI Approved :: MIT License
Classifier: Operating System :: OS Independent
Requires-Python: >=3.0
License-File: LICENSE
